setup.py
consulchecknagiosplugin/__init__.py
consulchecknagiosplugin/context.py
consulchecknagiosplugin/format.py
consulchecknagiosplugin/main.py
consulchecknagiosplugin/resources.py
consulchecknagiosplugin.egg-info/PKG-INFO
consulchecknagiosplugin.egg-info/SOURCES.txt
consulchecknagiosplugin.egg-info/dependency_links.txt
consulchecknagiosplugin.egg-info/entry_points.txt
consulchecknagiosplugin.egg-info/requires.txt
consulchecknagiosplugin.egg-info/top_level.txt