Metadata-Version: 1.0
Name: consulchecknagiosplugin
Version: 1.1.1
Summary: Consul Check Nagios Plugin
Home-page: http://locationlabs.com
Author: Location Labs
Author-email: info@locationlabs.com
License: UNKNOWN
Platform: UNKNOWN
